setup.cfg
setup.py
writeup/v0.py
writeup_tool.egg-info/PKG-INFO
writeup_tool.egg-info/SOURCES.txt
writeup_tool.egg-info/dependency_links.txt
writeup_tool.egg-info/entry_points.txt
writeup_tool.egg-info/top_level.txt